SimpleLyrics/__init__.py
SimpleLyrics/__main__.py
simplelyrics-0.0.4.dist-info/METADATA
simplelyrics-0.0.4.dist-info/WHEEL
simplelyrics-0.0.4.dist-info/entry_points.txt
simplelyrics-0.0.4.dist-info/top_level.txt
simplelyrics-0.0.4.dist-info/RECORD
